iam_check/__init__.py
iam_check/application_error.py
iam_check/argument_actions.py
iam_check/client.py
iam_check/config/default.yaml
iam_check/config.py
iam_check/doc/example_report_1.md
iam_check/doc/example_report_2.md
iam_check/doc/example_report_3.md
iam_check/iam_check.py
iam_check/lib/__init__.py
iam_check/lib/account_config.py
iam_check/lib/findings.py
iam_check/lib/iamCheck.py
iam_check/lib/iamPolicy.py
iam_check/lib/iamcheck_AccessAnalyzer.py
iam_check/lib/reporter.py
iam_check/lib/tfPlan.py
iam_check/parameters.py
iam_check/pytest.ini
iam_check/test/__init__.py
iam_check/test/aws_iam_policy.tf
iam_check/test/iam_policy/findings.json
iam_check/test/iam_policy/test.tf
iam_check/test/iam_policy/test_plan.json
iam_check/test/identity_policies/identity_findings.json
iam_check/test/identity_policies/identity_reference_policy.json
iam_check/test/identity_policies/test.tf
iam_check/test/identity_policies/test_plan.json
iam_check/test/multiple_policies/identity_findings.json
iam_check/test/multiple_policies/identity_reference_policy.json
iam_check/test/multiple_policies/resource_findings.json
iam_check/test/multiple_policies/resource_reference_policy.json
iam_check/test/multiple_policies/test.tf
iam_check/test/multiple_policies/test_plan.json
iam_check/test/no_access_granted/actions_findings.json
iam_check/test/no_access_granted/empty_findings.json
iam_check/test/no_access_granted/getObject_error_findings.json
iam_check/test/no_access_granted/getObject_example.json
iam_check/test/no_access_granted/getobject_findings.json
iam_check/test/no_access_granted/resources_and_actions_findings.json
iam_check/test/no_access_granted/resources_findings.json
iam_check/test/no_access_granted/test.tf
iam_check/test/no_access_granted/test_plan.json
iam_check/test/no_access_granted/test_plan.plan
iam_check/test/provider.tf
iam_check/test/public_access/public_access_findings.json
iam_check/test/public_access/test.tf
iam_check/test/public_access/test_plan.json
tf_policy_validator-0.0.9.dist-info/LICENSE
tf_policy_validator-0.0.9.dist-info/METADATA
tf_policy_validator-0.0.9.dist-info/WHEEL
tf_policy_validator-0.0.9.dist-info/entry_points.txt
tf_policy_validator-0.0.9.dist-info/RECORD
