Metadata-Version: 2.3
Name: tf-policy-validator
Version: 0.0.9
Summary: A command line tool that validates AWS IAM Policies in a Terraform template against AWS IAM best practices
License: MIT-0
Keywords: amazon,aws,aws-samples,eks,kubernetes,upgrade,iam_check
Author: Policy Validator Maintainers
Author-email: terraform-policy-validator@amazon.com
Requires-Python: >=3.8,<4.0
Classifier: License :: OSI Approved
Classifier: License :: OSI Approved :: MIT No Attribution License (MIT-0)
Classifier: Programming Language :: Python
Classifier: Programming Language :: Python :: 3
Classifier: Programming Language :: Python :: 3.8
Classifier: Programming Language :: Python :: 3.9
Classifier: Programming Language :: Python :: 3.10
Classifier: Programming Language :: Python :: 3.11
Classifier: Programming Language :: Python :: 3.12
Classifier: Programming Language :: Python :: 3.13
Requires-Dist: boto3 (>=1.34.124,<2.0.0)
Requires-Dist: pyyaml (>=6.0,<7.0)
